leopard_em/__init__.py
leopard_em/analysis/__init__.py
leopard_em/analysis/gev_fit_metric.py
leopard_em/analysis/match_template_peaks.py
leopard_em/analysis/pvalue_metric.py
leopard_em/analysis/utils.py
leopard_em/analysis/zscore_metric.py
leopard_em/backend/__init__.py
leopard_em/backend/core_match_template.py
leopard_em/backend/core_match_template_distributed.py
leopard_em/backend/core_refine_template.py
leopard_em/backend/cross_correlation.py
leopard_em/backend/distributed.py
leopard_em/backend/process_results.py
leopard_em/backend/utils.py
leopard_em/pydantic_models/__init__.py
leopard_em/pydantic_models/custom_types.py
leopard_em/pydantic_models/formats.py
leopard_em/pydantic_models/utils.py
leopard_em/pydantic_models/config/__init__.py
leopard_em/pydantic_models/config/computational_config.py
leopard_em/pydantic_models/config/correlation_filters.py
leopard_em/pydantic_models/config/defocus_search.py
leopard_em/pydantic_models/config/orientation_search.py
leopard_em/pydantic_models/config/pixel_size_search.py
leopard_em/pydantic_models/data_structures/__init__.py
leopard_em/pydantic_models/data_structures/optics_group.py
leopard_em/pydantic_models/data_structures/particle_stack.py
leopard_em/pydantic_models/managers/__init__.py
leopard_em/pydantic_models/managers/constrained_search_manager.py
leopard_em/pydantic_models/managers/match_template_manager.py
leopard_em/pydantic_models/managers/optimize_template_manager.py
leopard_em/pydantic_models/managers/refine_template_manager.py
leopard_em/pydantic_models/results/__init__.py
leopard_em/pydantic_models/results/match_template_result.py
leopard_em/utils/__init__.py
leopard_em/utils/cross_correlation.py
leopard_em/utils/data_io.py
leopard_em/utils/fourier_slice.py
leopard_em-1.1.1.dist-info/METADATA
leopard_em-1.1.1.dist-info/WHEEL
leopard_em-1.1.1.dist-info/licenses/LICENSE
leopard_em-1.1.1.dist-info/RECORD
