Metadata-Version: 2.4
Name: leopard_em
Version: 1.1.1
Summary: Location & Orientation of Particles found using Two-Dimensional Template Matching
Project-URL: homepage, https://github.com/Lucaslab-Berkeley/Leopard-EM
Project-URL: repository, https://github.com/Lucaslab-Berkeley/Leopard-EM
Author-email: Matthew Giammar <matthew_giammar@berkeley.edu>, Josh Dickerson <jdickerson@berkeley.edu>
License: BSD-3-Clause
License-File: LICENSE
Classifier: Development Status :: 3 - Alpha
Classifier: License :: OSI Approved :: BSD License
Classifier: Programming Language :: Python :: 3
Classifier: Programming Language :: Python :: 3.10
Classifier: Programming Language :: Python :: 3.11
Classifier: Programming Language :: Python :: 3.12
Classifier: Programming Language :: Python :: 3.13
Classifier: Typing :: Typed
Requires-Python: >=3.10
Requires-Dist: einops
Requires-Dist: lmfit
Requires-Dist: mrcfile
Requires-Dist: numpy
Requires-Dist: pandas
Requires-Dist: pydantic
Requires-Dist: pyyaml
Requires-Dist: roma
Requires-Dist: torch
Requires-Dist: torch-fourier-filter>=v0.2.6
Requires-Dist: torch-fourier-slice>=v0.4.0
Requires-Dist: torch-so3>=v0.2.0
Requires-Dist: tqdm
Requires-Dist: ttsim3d>=v0.4.0
Requires-Dist: types-pyyaml
Requires-Dist: zenodo-get
Provides-Extra: dev
Requires-Dist: ipython; extra == 'dev'
Requires-Dist: mypy; extra == 'dev'
Requires-Dist: pdbpp; extra == 'dev'
Requires-Dist: pre-commit; extra == 'dev'
Requires-Dist: pylint; extra == 'dev'
Requires-Dist: rich; extra == 'dev'
Requires-Dist: ruff; extra == 'dev'
Provides-Extra: docs
Requires-Dist: mkdocs; extra == 'docs'
Requires-Dist: mkdocs-autoapi; extra == 'docs'
Requires-Dist: mkdocs-autorefs; extra == 'docs'
Requires-Dist: mkdocs-gallery; extra == 'docs'
Requires-Dist: mkdocs-inline-select-svg-plugin; extra == 'docs'
Requires-Dist: mkdocs-jupyter; extra == 'docs'
Requires-Dist: mkdocs-material; extra == 'docs'
Requires-Dist: mkdocstrings[python]; extra == 'docs'
Requires-Dist: python-markdown-math; extra == 'docs'
Provides-Extra: test
Requires-Dist: pytest; extra == 'test'
Requires-Dist: pytest-cov; extra == 'test'
